email_validate/__init__.py
email_validate/constants.py
email_validate/dns_check.py
email_validate/domainlist_check.py
email_validate/email_address.py
email_validate/email_validate.py
email_validate/exceptions.py
email_validate/regex_check.py
email_validate/smtp_check.py
email_validate/data/emails_filtered.txt
email_validate-1.1.2.dist-info/AUTHORS
email_validate-1.1.2.dist-info/LICENSE
email_validate-1.1.2.dist-info/METADATA
email_validate-1.1.2.dist-info/WHEEL
email_validate-1.1.2.dist-info/top_level.txt
email_validate-1.1.2.dist-info/RECORD
