Metadata-Version: 2.1
Name: email-validate
Version: 1.1.2
Summary: Email validator with regex, blacklisted domains and SMTP checking.
Home-page: https://github.com/containerpi/email_validate
Author: CPILab
Author-email: hello@containerpi.com
License: LGPL
Keywords: email validation verification mx verify
Platform: UNKNOWN
Classifier: Development Status :: 2 - Pre-Alpha
Classifier: Intended Audience :: Developers
Classifier: Operating System :: OS Independent
Classifier: Programming Language :: Python
Classifier: Programming Language :: Python :: 3
Classifier: Programming Language :: Python :: 3 :: Only
Classifier: Programming Language :: Python :: 3.6
Classifier: Programming Language :: Python :: 3.7
Classifier: Programming Language :: Python :: 3.8
Classifier: Programming Language :: Python :: 3.9
Classifier: Topic :: Software Development :: Libraries :: Application Frameworks
Classifier: Topic :: Software Development :: Libraries :: Python Modules
